kolibri2zim/__about__.py
kolibri2zim/__init__.py
kolibri2zim/constants.py
kolibri2zim/database.py
kolibri2zim/debug.py
kolibri2zim/entrypoint.py
kolibri2zim/nodes.py
kolibri2zim/processing.py
kolibri2zim/scraper.py
kolibri2zim/templates/about.html
kolibri2zim/templates/audio.html
kolibri2zim/templates/base.html
kolibri2zim/templates/card.html
kolibri2zim/templates/document.html
kolibri2zim/templates/epub.html
kolibri2zim/templates/kolibri-logo.png
kolibri2zim/templates/node_meta.html
kolibri2zim/templates/perseus_exercise.html
kolibri2zim/templates/topic.html
kolibri2zim/templates/video.html
kolibri2zim/templates/assets/document.js
kolibri2zim/templates/assets/epub_embed.css
kolibri2zim/templates/assets/epub_embed.html
kolibri2zim/templates/assets/epub_embed.js
kolibri2zim/templates/assets/perseus_exercise.js
kolibri2zim-1.2.1.dist-info/METADATA
kolibri2zim-1.2.1.dist-info/WHEEL
kolibri2zim-1.2.1.dist-info/entry_points.txt
kolibri2zim-1.2.1.dist-info/licenses/LICENSE
kolibri2zim-1.2.1.dist-info/RECORD
