Metadata-Version: 2.1
Name: kolibri2zim
Version: 1.2.1
Summary: Make ZIM file from Kolibri Channels
Project-URL: Donate, https://www.kiwix.org/en/support-us/
Project-URL: Homepage, https://github.com/openzim/kolibri
Author-email: openZIM <dev@openzim.org>
License: GPL-3.0-or-later
License-File: LICENSE
Keywords: kolibri,offline,openzim,zim
Classifier: License :: OSI Approved :: GNU General Public License v3 or later (GPLv3+)
Classifier: Programming Language :: Python :: 3
Classifier: Programming Language :: Python :: 3.12
Requires-Python: <3.13,>=3.12
Requires-Dist: beautifulsoup4==4.9.3
Requires-Dist: jinja2==3.1.3
Requires-Dist: kiwixstorage==0.8.3
Requires-Dist: pif==0.8.2
Requires-Dist: retrying==1.3.4
Requires-Dist: zimscraperlib==3.3.1
Provides-Extra: check
Requires-Dist: pyright==1.1.350; extra == 'check'
Provides-Extra: dev
Requires-Dist: debugpy==1.8.1; extra == 'dev'
Requires-Dist: kolibri2zim[check]; extra == 'dev'
Requires-Dist: kolibri2zim[lint]; extra == 'dev'
Requires-Dist: kolibri2zim[scripts]; extra == 'dev'
Requires-Dist: kolibri2zim[test]; extra == 'dev'
Requires-Dist: pre-commit==3.6.1; extra == 'dev'
Provides-Extra: lint
Requires-Dist: black==24.2.0; extra == 'lint'
Requires-Dist: ruff==0.2.1; extra == 'lint'
Provides-Extra: scripts
Requires-Dist: invoke==2.2.0; extra == 'scripts'
Provides-Extra: test
Requires-Dist: coverage==7.4.1; extra == 'test'
Requires-Dist: pytest==8.0.0; extra == 'test'
